fk_graph/__init__.py
fk_graph/cli.py
fk_graph/cytoscape.py
fk_graph/data_setup.py
fk_graph/edge_excluders.py
fk_graph/graph.py
fk_graph/plot_graph.py
fk_graph/plotly_functions.py
fk_graph-0.0.15.dist-info/METADATA
fk_graph-0.0.15.dist-info/WHEEL
fk_graph-0.0.15.dist-info/entry_points.txt
fk_graph-0.0.15.dist-info/licenses/LICENSE
fk_graph-0.0.15.dist-info/RECORD
